htmltaglib/__init__.py
htmltaglib/htmltaglib.py
htmltaglib-1.2.1.dist-info/METADATA
htmltaglib-1.2.1.dist-info/WHEEL
htmltaglib-1.2.1.dist-info/licenses/LICENSE
htmltaglib-1.2.1.dist-info/RECORD
