Metadata-Version: 2.1
Name: htmltaglib
Version: 1.2.1
Summary: Designed to be an easy-to-implement HTML Element source for Bottle (and other) projects.
Project-URL: Homepage, https://github.com/micahhanevich/HTMLTagLib
Project-URL: Bug Tracker, https://github.com/micahhanevich/HTMLTagLib/issues
Author-email: Micah J Hanevich <micahjhanevich@gmail.com>
License-File: LICENSE
Classifier: License :: OSI Approved :: MIT License
Classifier: Operating System :: OS Independent
Classifier: Programming Language :: Python :: 3
Requires-Python: >=3.7
